<?xml version="1.0" encoding="utf-8"?>
<annotation>
	<folder>--</folder>
	<filename>--</filename>
	<path>--</path>
	<source>
		<database>Unknown</database>
	</source>
	<size>
		<width>1729</width>
		<height>1240</height>
		<depth>3</depth>
	</size>
	<segmented>0</segmented>
	<object>
		<name>WF</name>
		<pose>Unspecified</pose>
		<truncated>0</truncated>
		<difficult>0</difficult>
		<bndbox>
			<xmin>2383</xmin>
			<ymin>691</ymin>
			<xmax>2413</xmax>
			<ymax>727</ymax>
		</bndbox>
	</object>
	<object>
		<name>WF</name>
		<pose>Unspecified</pose>
		<truncated>0</truncated>
		<difficult>0</difficult>
		<bndbox>
			<xmin>2383</xmin>
			<ymin>646</ymin>
			<xmax>2419</xmax>
			<ymax>669</ymax>
		</bndbox>
	</object>
	<object>
		<name>WF</name>
		<pose>Unspecified</pose>
		<truncated>0</truncated>
		<difficult>0</difficult>
		<bndbox>
			<xmin>2036</xmin>
			<ymin>597</ymin>
			<xmax>2075</xmax>
			<ymax>649</ymax>
		</bndbox>
	</object>
	<object>
		<name>WF</name>
		<pose>Unspecified</pose>
		<truncated>0</truncated>
		<difficult>0</difficult>
		<bndbox>
			<xmin>2619</xmin>
			<ymin>529</ymin>
			<xmax>2700</xmax>
			<ymax>572</ymax>
		</bndbox>
	</object>
	<object>
		<name>WF</name>
		<pose>Unspecified</pose>
		<truncated>0</truncated>
		<difficult>0</difficult>
		<bndbox>
			<xmin>2715</xmin>
			<ymin>619</ymin>
			<xmax>2774</xmax>
			<ymax>659</ymax>
		</bndbox>
	</object>
	<object>
		<name>WF</name>
		<pose>Unspecified</pose>
		<truncated>0</truncated>
		<difficult>0</difficult>
		<bndbox>
			<xmin>2875</xmin>
			<ymin>606</ymin>
			<xmax>2913</xmax>
			<ymax>635</ymax>
		</bndbox>
	</object>
	<object>
		<name>WF</name>
		<pose>Unspecified</pose>
		<truncated>0</truncated>
		<difficult>0</difficult>
		<bndbox>
			<xmin>2349</xmin>
			<ymin>1240</ymin>
			<xmax>2431</xmax>
			<ymax>1286</ymax>
		</bndbox>
	</object>
	<object>
		<name>WF</name>
		<pose>Unspecified</pose>
		<truncated>0</truncated>
		<difficult>0</difficult>
		<bndbox>
			<xmin>1730</xmin>
			<ymin>1077</ymin>
			<xmax>1770</xmax>
			<ymax>1126</ymax>
		</bndbox>
	</object>
	<object>
		<name>WF</name>
		<pose>Unspecified</pose>
		<truncated>0</truncated>
		<difficult>0</difficult>
		<bndbox>
			<xmin>2864</xmin>
			<ymin>1241</ymin>
			<xmax>2949</xmax>
			<ymax>1307</ymax>
		</bndbox>
	</object>
	<object>
		<name>WF</name>
		<pose>Unspecified</pose>
		<truncated>0</truncated>
		<difficult>0</difficult>
		<bndbox>
			<xmin>2699</xmin>
			<ymin>936</ymin>
			<xmax>2758</xmax>
			<ymax>996</ymax>
		</bndbox>
	</object>
	<object>
		<name>WF</name>
		<pose>Unspecified</pose>
		<truncated>0</truncated>
		<difficult>0</difficult>
		<bndbox>
			<xmin>2770</xmin>
			<ymin>941</ymin>
			<xmax>2819</xmax>
			<ymax>1004</ymax>
		</bndbox>
	</object>
	<object>
		<name>WF</name>
		<pose>Unspecified</pose>
		<truncated>0</truncated>
		<difficult>0</difficult>
		<bndbox>
			<xmin>2875</xmin>
			<ymin>1513</ymin>
			<xmax>2960</xmax>
			<ymax>1586</ymax>
		</bndbox>
	</object>
	<object>
		<name>WF</name>
		<pose>Unspecified</pose>
		<truncated>0</truncated>
		<difficult>0</difficult>
		<bndbox>
			<xmin>4428</xmin>
			<ymin>658</ymin>
			<xmax>4489</xmax>
			<ymax>707</ymax>
		</bndbox>
	</object>
	<object>
		<name>WF</name>
		<pose>Unspecified</pose>
		<truncated>0</truncated>
		<difficult>0</difficult>
		<bndbox>
			<xmin>4289</xmin>
			<ymin>638</ymin>
			<xmax>4352</xmax>
			<ymax>688</ymax>
		</bndbox>
	</object>
	<object>
		<name>WF</name>
		<pose>Unspecified</pose>
		<truncated>0</truncated>
		<difficult>0</difficult>
		<bndbox>
			<xmin>3906</xmin>
			<ymin>588</ymin>
			<xmax>3966</xmax>
			<ymax>635</ymax>
		</bndbox>
	</object>
	<object>
		<name>WF</name>
		<pose>Unspecified</pose>
		<truncated>0</truncated>
		<difficult>0</difficult>
		<bndbox>
			<xmin>3600</xmin>
			<ymin>1218</ymin>
			<xmax>3670</xmax>
			<ymax>1282</ymax>
		</bndbox>
	</object>
	<object>
		<name>WF</name>
		<pose>Unspecified</pose>
		<truncated>0</truncated>
		<difficult>0</difficult>
		<bndbox>
			<xmin>3661</xmin>
			<ymin>1457</ymin>
			<xmax>3736</xmax>
			<ymax>1530</ymax>
		</bndbox>
	</object>
	<object>
		<name>WF</name>
		<pose>Unspecified</pose>
		<truncated>0</truncated>
		<difficult>0</difficult>
		<bndbox>
			<xmin>3823</xmin>
			<ymin>1557</ymin>
			<xmax>3892</xmax>
			<ymax>1599</ymax>
		</bndbox>
	</object>
	<object>
		<name>WF</name>
		<pose>Unspecified</pose>
		<truncated>0</truncated>
		<difficult>0</difficult>
		<bndbox>
			<xmin>4019</xmin>
			<ymin>1566</ymin>
			<xmax>4091</xmax>
			<ymax>1618</ymax>
		</bndbox>
	</object>
	<object>
		<name>WF</name>
		<pose>Unspecified</pose>
		<truncated>0</truncated>
		<difficult>0</difficult>
		<bndbox>
			<xmin>4141</xmin>
			<ymin>1529</ymin>
			<xmax>4188</xmax>
			<ymax>1582</ymax>
		</bndbox>
	</object>
	<object>
		<name>WF</name>
		<pose>Unspecified</pose>
		<truncated>0</truncated>
		<difficult>0</difficult>
		<bndbox>
			<xmin>4756</xmin>
			<ymin>1477</ymin>
			<xmax>4816</xmax>
			<ymax>1536</ymax>
		</bndbox>
	</object>
	<object>
		<name>WF</name>
		<pose>Unspecified</pose>
		<truncated>0</truncated>
		<difficult>0</difficult>
		<bndbox>
			<xmin>4645</xmin>
			<ymin>1079</ymin>
			<xmax>4688</xmax>
			<ymax>1144</ymax>
		</bndbox>
	</object>
	<object>
		<name>WF</name>
		<pose>Unspecified</pose>
		<truncated>0</truncated>
		<difficult>0</difficult>
		<bndbox>
			<xmin>4152</xmin>
			<ymin>1096</ymin>
			<xmax>4219</xmax>
			<ymax>1168</ymax>
		</bndbox>
	</object>
	<object>
		<name>WF</name>
		<pose>Unspecified</pose>
		<truncated>0</truncated>
		<difficult>0</difficult>
		<bndbox>
			<xmin>4364</xmin>
			<ymin>946</ymin>
			<xmax>4477</xmax>
			<ymax>1026</ymax>
		</bndbox>
	</object>
	<object>
		<name>WF</name>
		<pose>Unspecified</pose>
		<truncated>0</truncated>
		<difficult>0</difficult>
		<bndbox>
			<xmin>4611</xmin>
			<ymin>915</ymin>
			<xmax>4678</xmax>
			<ymax>958</ymax>
		</bndbox>
	</object>
	<object>
		<name>WF</name>
		<pose>Unspecified</pose>
		<truncated>0</truncated>
		<difficult>0</difficult>
		<bndbox>
			<xmin>4781</xmin>
			<ymin>829</ymin>
			<xmax>4859</xmax>
			<ymax>874</ymax>
		</bndbox>
	</object>
	<object>
		<name>WF</name>
		<pose>Unspecified</pose>
		<truncated>0</truncated>
		<difficult>0</difficult>
		<bndbox>
			<xmin>4981</xmin>
			<ymin>976</ymin>
			<xmax>5044</xmax>
			<ymax>1036</ymax>
		</bndbox>
	</object>
	<object>
		<name>WF</name>
		<pose>Unspecified</pose>
		<truncated>0</truncated>
		<difficult>0</difficult>
		<bndbox>
			<xmin>5048</xmin>
			<ymin>733</ymin>
			<xmax>5119</xmax>
			<ymax>799</ymax>
		</bndbox>
	</object>
	<object>
		<name>WF</name>
		<pose>Unspecified</pose>
		<truncated>0</truncated>
		<difficult>0</difficult>
		<bndbox>
			<xmin>2013</xmin>
			<ymin>2479</ymin>
			<xmax>2097</xmax>
			<ymax>2547</ymax>
		</bndbox>
	</object>
	<object>
		<name>WF</name>
		<pose>Unspecified</pose>
		<truncated>0</truncated>
		<difficult>0</difficult>
		<bndbox>
			<xmin>2345</xmin>
			<ymin>2574</ymin>
			<xmax>2450</xmax>
			<ymax>2618</ymax>
		</bndbox>
	</object>
	<object>
		<name>WF</name>
		<pose>Unspecified</pose>
		<truncated>0</truncated>
		<difficult>0</difficult>
		<bndbox>
			<xmin>2552</xmin>
			<ymin>2624</ymin>
			<xmax>2617</xmax>
			<ymax>2671</ymax>
		</bndbox>
	</object>
	<object>
		<name>WF</name>
		<pose>Unspecified</pose>
		<truncated>0</truncated>
		<difficult>0</difficult>
		<bndbox>
			<xmin>2639</xmin>
			<ymin>2402</ymin>
			<xmax>2717</xmax>
			<ymax>2452</ymax>
		</bndbox>
	</object>
	<object>
		<name>WF</name>
		<pose>Unspecified</pose>
		<truncated>0</truncated>
		<difficult>0</difficult>
		<bndbox>
			<xmin>2810</xmin>
			<ymin>2349</ymin>
			<xmax>2861</xmax>
			<ymax>2405</ymax>
		</bndbox>
	</object>
	<object>
		<name>WF</name>
		<pose>Unspecified</pose>
		<truncated>0</truncated>
		<difficult>0</difficult>
		<bndbox>
			<xmin>2860</xmin>
			<ymin>2410</ymin>
			<xmax>2922</xmax>
			<ymax>2433</ymax>
		</bndbox>
	</object>
	<object>
		<name>WF</name>
		<pose>Unspecified</pose>
		<truncated>0</truncated>
		<difficult>0</difficult>
		<bndbox>
			<xmin>2472</xmin>
			<ymin>2040</ymin>
			<xmax>2583</xmax>
			<ymax>2105</ymax>
		</bndbox>
	</object>
	<object>
		<name>WF</name>
		<pose>Unspecified</pose>
		<truncated>0</truncated>
		<difficult>0</difficult>
		<bndbox>
			<xmin>2650</xmin>
			<ymin>2008</ymin>
			<xmax>2708</xmax>
			<ymax>2057</ymax>
		</bndbox>
	</object>
	<object>
		<name>WF</name>
		<pose>Unspecified</pose>
		<truncated>0</truncated>
		<difficult>0</difficult>
		<bndbox>
			<xmin>4533</xmin>
			<ymin>1994</ymin>
			<xmax>4605</xmax>
			<ymax>2032</ymax>
		</bndbox>
	</object>
	<object>
		<name>WF</name>
		<pose>Unspecified</pose>
		<truncated>0</truncated>
		<difficult>0</difficult>
		<bndbox>
			<xmin>4677</xmin>
			<ymin>1963</ymin>
			<xmax>4747</xmax>
			<ymax>2018</ymax>
		</bndbox>
	</object>
	<object>
		<name>WF</name>
		<pose>Unspecified</pose>
		<truncated>0</truncated>
		<difficult>0</difficult>
		<bndbox>
			<xmin>4772</xmin>
			<ymin>1886</ymin>
			<xmax>4817</xmax>
			<ymax>1918</ymax>
		</bndbox>
	</object>
	<object>
		<name>WF</name>
		<pose>Unspecified</pose>
		<truncated>0</truncated>
		<difficult>0</difficult>
		<bndbox>
			<xmin>4797</xmin>
			<ymin>1872</ymin>
			<xmax>4864</xmax>
			<ymax>1902</ymax>
		</bndbox>
	</object>
	<object>
		<name>WF</name>
		<pose>Unspecified</pose>
		<truncated>0</truncated>
		<difficult>0</difficult>
		<bndbox>
			<xmin>4461</xmin>
			<ymin>2691</ymin>
			<xmax>4533</xmax>
			<ymax>2750</ymax>
		</bndbox>
	</object>
	<object>
		<name>WF</name>
		<pose>Unspecified</pose>
		<truncated>0</truncated>
		<difficult>0</difficult>
		<bndbox>
			<xmin>4561</xmin>
			<ymin>2621</ymin>
			<xmax>4611</xmax>
			<ymax>2671</ymax>
		</bndbox>
	</object>
	<object>
		<name>WF</name>
		<pose>Unspecified</pose>
		<truncated>0</truncated>
		<difficult>0</difficult>
		<bndbox>
			<xmin>3900</xmin>
			<ymin>2824</ymin>
			<xmax>3939</xmax>
			<ymax>2850</ymax>
		</bndbox>
	</object>
	<object>
		<name>WF</name>
		<pose>Unspecified</pose>
		<truncated>0</truncated>
		<difficult>0</difficult>
		<bndbox>
			<xmin>3503</xmin>
			<ymin>2815</ymin>
			<xmax>3542</xmax>
			<ymax>2857</ymax>
		</bndbox>
	</object>
	<object>
		<name>WF</name>
		<pose>Unspecified</pose>
		<truncated>0</truncated>
		<difficult>0</difficult>
		<bndbox>
			<xmin>5072</xmin>
			<ymin>2496</ymin>
			<xmax>5145</xmax>
			<ymax>2566</ymax>
		</bndbox>
	</object>
	<object>
		<name>WF</name>
		<pose>Unspecified</pose>
		<truncated>0</truncated>
		<difficult>0</difficult>
		<bndbox>
			<xmin>4859</xmin>
			<ymin>2271</ymin>
			<xmax>4945</xmax>
			<ymax>2305</ymax>
		</bndbox>
	</object>
	<object>
		<name>WF</name>
		<pose>Unspecified</pose>
		<truncated>0</truncated>
		<difficult>0</difficult>
		<bndbox>
			<xmin>4636</xmin>
			<ymin>2213</ymin>
			<xmax>4738</xmax>
			<ymax>2272</ymax>
		</bndbox>
	</object>
	<object>
		<name>WF</name>
		<pose>Unspecified</pose>
		<truncated>0</truncated>
		<difficult>0</difficult>
		<bndbox>
			<xmin>4267</xmin>
			<ymin>2069</ymin>
			<xmax>4334</xmax>
			<ymax>2122</ymax>
		</bndbox>
	</object>
	<object>
		<name>WF</name>
		<pose>Unspecified</pose>
		<truncated>0</truncated>
		<difficult>0</difficult>
		<bndbox>
			<xmin>3917</xmin>
			<ymin>1879</ymin>
			<xmax>4014</xmax>
			<ymax>1927</ymax>
		</bndbox>
	</object>
	<object>
		<name>WF</name>
		<pose>Unspecified</pose>
		<truncated>0</truncated>
		<difficult>0</difficult>
		<bndbox>
			<xmin>4720</xmin>
			<ymin>2691</ymin>
			<xmax>4753</xmax>
			<ymax>2724</ymax>
		</bndbox>
	</object>
</annotation>